LICENSE
tvw_scraper/__init__.py
tvw_scraper/models.py
tvw_scraper/rest.py
tvw_scraper/schemas.py
tvw_scraper/scraper.py
tvw_scraper-0.0.17.dist-info/LICENSE
tvw_scraper-0.0.17.dist-info/WHEEL
tvw_scraper-0.0.17.dist-info/METADATA
tvw_scraper-0.0.17.dist-info/RECORD
